auto_mlops/__init__.py
auto_mlops/deployer.py
auto_mlops/pipeline_wrapper.py
auto_mlops/utils.py
auto_mlops-0.1.12.dist-info/WHEEL
auto_mlops-0.1.12.dist-info/METADATA
auto_mlops-0.1.12.dist-info/RECORD
