Metadata-Version: 2.1
Name: auto-mlops
Version: 0.1.12
Summary: Deploy your model in one line of code
Author: Datarmada
Author-email: contact@datarmada.com
Requires-Python: >=3.6,<4.0
Classifier: Programming Language :: Python :: 3
Classifier: Programming Language :: Python :: 3.6
Classifier: Programming Language :: Python :: 3.7
Classifier: Programming Language :: Python :: 3.8
Requires-Dist: cloudpickle (>=1.3.0,<2.0.0)
Requires-Dist: requests (>=2.23.0,<3.0.0)
Requires-Dist: scikit-learn (>=0.22.1,<0.23.0)
